Workbook

Sheet Historical Data
A1: Historical Data
A2: Year | B2: 2023 | C2: 2024 | D2: 2025
A3: Revenue | B3: 26974 | C3: 60922 | D3: 130497
A4: Revenue Growth | C4: =(C3/B3) -1 -> 1.2585453 | D4: =(D3/C3) -1 -> 1.1420341
A5: Operating Income | B5: 4224 | C5: 32972 | D5: 81453
A6: Depreciation | B6: 1544 | C6: 1508 | D6: 1864
A7: CapEx | B7: 1833 | C7: 1069 | D7: 3236

Sheet DCF Model
A1: Assumptions
A2: Revenue Growth Year 1 | B2: 0.25 | F2: Years | G2: 2026 | H2: 2027 | I2: 2028 | J2: 2029 | K2: 2030
A3: Revenue Growth Year 2 | B3: 0.2 | F3: EBIT % | G3: 0.58 | H3: 0.56 | I3: 0.53 | J3: 0.5 | K3: 0.48
A4: Revenue Growth Year 3 | B4: 0.15
A5: Revenue Growth Year 4 | B5: 0.1
A6: Revenue Growth Year 5 | B6: 0.08
A7: Tax Rate | B7: 0.21
A8: WACC | B8: 0.11
A9: Terminal Growth | B9: 0.03
A11: D&A % of Revenue | B11: 0.014
A12: CapEx % of Revenue | B12: 0.025
A13: NWC % of Rev Change | B13: 0.145

Sheet Projections
A1: Year | B1: 2026 | C1: 2027 | D1: 2028 | E1: 2029 | F1: 2030
A2: Revenue | B2: ='Historical Data'!D3*(1+'DCF Model'!$B$2) -> 163121.25 | C2: =B2*(1+'DCF Model'!B3) -> 195745.5 | D2: =C2*(1+'DCF Model'!B4) -> 225107.32 | E2: =D2*(1+'DCF Model'!B5) -> 247618.06 | F2: =E2*(1+'DCF Model'!B6) -> 267427.5 | I2: Sensitivy Table
A3: EBIT | B3: =B2 * 'DCF Model'!G3 -> 94610.325 | C3: =C2 * 'DCF Model'!H3 -> 109617.48 | D3: =D2 * 'DCF Model'!I3 -> 119306.88 | E3: =E2 * 'DCF Model'!J3 -> 123809.03 | F3: =F2 * 'DCF Model'!K3 -> 128365.2 | I3: WACC | J3: Implied Share Prices
A4: NOPAT | B4: =B3*(1-'DCF Model'!$B$7) -> 74742.157 | C4: =C3*(1-'DCF Model'!$B$7) -> 86597.809 | D4: =D3*(1-'DCF Model'!$B$7) -> 94252.437 | E4: =E3*(1-'DCF Model'!$B$7) -> 97809.133 | F4: =F3*(1-'DCF Model'!$B$7) -> 101408.51 | I4: 0.09 | J4: 56.08
A5: D&A | B5: =B2 * 'DCF Model'!$B$11 -> 2283.6975 | C5: =C2 * 'DCF Model'!$B$11 -> 2740.437 | D5: =D2 * 'DCF Model'!$B$11 -> 3151.5025 | E5: =E2 * 'DCF Model'!$B$11 -> 3466.6528 | F5: =F2 * 'DCF Model'!$B$11 -> 3743.985 | I5: 0.1 | J5: 47.94
A6: CapEx | B6: =B2 * 'DCF Model'!$B$12 -> 4078.0312 | C6: =C2 * 'DCF Model'!$B$12 -> 4893.6375 | D6: =D2 * 'DCF Model'!$B$12 -> 5627.6831 | E6: =E2 * 'DCF Model'!$B$12 -> 6190.4514 | F6: =F2 * 'DCF Model'!$B$12 -> 6685.6876 | I6: 0.11 | J6: 41.84
A7: Change in NWC | B7: =(B2 - 'Historical Data'!D3) * 'DCF Model'!$B$13 -> 4730.5162 | C7: =(C2 - B2) * 'DCF Model'!$B$13 -> 4730.5162 | D7: =(D2 - C2) * 'DCF Model'!$B$13 -> 4257.4646 | E7: =(E2 - D2) * 'DCF Model'!$B$13 -> 3264.0562 | F7: =(F2 - E2) * 'DCF Model'!$B$13 -> 2872.3695 | I7: 0.12 | J7: 37.09
A8: FCF | B8: =B4+B5-B6-B7 -> 68217.307 | C8: =C4+C5-C6-C7 -> 79714.092 | D8: =D4+D5-D6-D7 -> 87518.792 | E8: =E4+E5-E6-E7 -> 91821.278 | F8: =F4+F5-F6-F7 -> 95594.437
A9: Discount Factor | B9: =1/(1+'DCF Model'!$B$8)^1 -> 0.9009009 | C9: =1/(1+'DCF Model'!$B$8)^2 -> 0.81162243 | D9: =1/(1+'DCF Model'!$B$8)^3 -> 0.73119138 | E9: =1/(1+'DCF Model'!$B$8)^4 -> 0.65873097 | F9: =1/(1+'DCF Model'!$B$8)^5 -> 0.59345133
A11: Valuation | I11: NVIDIA DCF Summary
A12: Year | B12: 2026 | C12: 2027 | D12: 2028 | E12: 2029 | F12: 2030 | I12: WACC | J12: 0.11
A13: PV of FCF | B13: =B8 * B9 -> 61457.033 | C13: =C8 * C9 -> 64697.746 | D13: =D8 * D9 -> 63992.986 | E13: =E8 * E9 -> 60485.52 | F13: =F8 * F9 -> 56730.645 | I13: Terminal Growth | J13: 0.03
A14: Terminal Value | F14: =F8*(1+'DCF Model'!$B$9)/('DCF Model'!$B$8-'DCF Model'!$B$9) -> 1230778.4 | I14: Enterprise Value | J14: 1037771
A15: PV of Terminal Value | F15: =F14 * F9 -> 730407.06 | I15: Implied Share Price | J15: 41.84
A16: Enterprise Value | F16: =SUM(B13:F13) + F15 -> 1037771
A19: Implied Share Price | B19: =F16/24804 -> 41.838856
